twitch_highlights/__init__.py
twitch_highlights/acr_cloud.py
twitch_highlights/clip_edit.py
twitch_highlights/twitch_api.py
witch_highlights-1.1.1.dist-info/LICENSE
witch_highlights-1.1.1.dist-info/METADATA
witch_highlights-1.1.1.dist-info/WHEEL
witch_highlights-1.1.1.dist-info/top_level.txt
witch_highlights-1.1.1.dist-info/RECORD
