Metadata-Version: 2.1
Name: witch-highlights
Version: 1.1.1
Summary: An OS-independent and easy-to-use module for creating highlight videos from trending Twitch clips. Twitch highlight videos can be created by either specifying a category or a list of streamer names.
Home-page: https://github.com/pelledrijver/witch-highlights
Author: Pelle Drijver
Author-email: pelledrijver@gmail.com
License: Apache License 2.0
Keywords: twitch,twitch highlights,twitch clips,twitch compilation
Platform: UNKNOWN
Classifier: Programming Language :: Python :: 3
Classifier: Programming Language :: Python :: 3.6
Classifier: Programming Language :: Python :: 3.7
Classifier: Programming Language :: Python :: 3.8
Classifier: License :: OSI Approved :: Apache Software License
Classifier: Operating System :: OS Independent
License-File: LICENSE
Requires-Dist: requests
Requires-Dist: datetime
Requires-Dist: moviepy (>=1.0.3)
Requires-Dist: python-slugify (>=4.0)
